tgSecuLib/__init__.py
tgSecuLib/main.py
tgSecuLib-0.2.3.dist-info/LICENSE
tgSecuLib-0.2.3.dist-info/METADATA
tgSecuLib-0.2.3.dist-info/WHEEL
tgSecuLib-0.2.3.dist-info/top_level.txt
tgSecuLib-0.2.3.dist-info/RECORD
