Metadata-Version: 2.2
Name: tgSecuLib
Version: 0.2.3
Summary: This is a security module
Author-email: jffwxs <kvostrecova0207@mail.ru>
License: MIT
License-File: LICENSE
